vtat/__init__.py
vtat/vtat.py
vtat-0.0.9.dist-info/LICENSE
vtat-0.0.9.dist-info/METADATA
vtat-0.0.9.dist-info/WHEEL
vtat-0.0.9.dist-info/top_level.txt
vtat-0.0.9.dist-info/RECORD
