Metadata-Version: 2.1
Name: vtat
Version: 0.0.9
Summary: A simple ACL system
Home-page: UNKNOWN
Author: vtat
Author-email: askofback@gmail.com
License: MIT
Platform: UNKNOWN
Classifier: Programming Language :: Python :: 3
Classifier: Programming Language :: Python :: 3.8
Classifier: License :: OSI Approved :: MIT License
Classifier: Operating System :: OS Independent
Requires-Python: >=3.6
